dlubal/__init__.py
dlubal/api/__init__.py
dlubal/api/common/__init__.py
dlubal/api/common/common_messages_pb2.py
dlubal/api/common/common_messages_pb2.pyi
dlubal/api/common/common_pb2.py
dlubal/api/common/common_pb2.pyi
dlubal/api/common/connection.py
dlubal/api/common/exceptions.py
dlubal/api/common/model_id_pb2.py
dlubal/api/common/model_id_pb2.pyi
dlubal/api/common/options_pb2.py
dlubal/api/common/options_pb2.pyi
dlubal/api/common/packing.py
dlubal/api/common/table.py
dlubal/api/common/table_data_pb2.py
dlubal/api/common/table_data_pb2.pyi
dlubal/api/common/tree_table.py
dlubal/api/common/import_export/__init__.py
dlubal/api/common/import_export/export_attributes_pb2.py
dlubal/api/common/import_export/export_attributes_pb2.pyi
dlubal/api/common/import_export/import_attributes_pb2.py
dlubal/api/common/import_export/import_attributes_pb2.pyi
dlubal/api/rfem/__init__.py
dlubal/api/rfem/all_pb2.py
dlubal/api/rfem/all_pb2.pyi
dlubal/api/rfem/application.py
dlubal/api/rfem/application_pb2.py
dlubal/api/rfem/application_pb2.pyi
dlubal/api/rfem/application_pb2_grpc.py
dlubal/api/rfem/base_data_pb2.py
dlubal/api/rfem/base_data_pb2.pyi
dlubal/api/rfem/design_addons_pb2.py
dlubal/api/rfem/design_addons_pb2.pyi
dlubal/api/rfem/object_id_pb2.py
dlubal/api/rfem/object_id_pb2.pyi
dlubal/api/rfem/object_type_pb2.py
dlubal/api/rfem/object_type_pb2.pyi
dlubal/api/rfem/referenced_object_pb2.py
dlubal/api/rfem/referenced_object_pb2.pyi
dlubal/api/rfem/aluminum_design/__init__.py
dlubal/api/rfem/aluminum_design/aluminum_boundary_conditions_pb2.py
dlubal/api/rfem/aluminum_design/aluminum_boundary_conditions_pb2.pyi
dlubal/api/rfem/aluminum_design/aluminum_effective_lengths_pb2.py
dlubal/api/rfem/aluminum_design/aluminum_effective_lengths_pb2.pyi
dlubal/api/rfem/aluminum_design/aluminum_member_local_cross_section_reduction_pb2.py
dlubal/api/rfem/aluminum_design/aluminum_member_local_cross_section_reduction_pb2.pyi
dlubal/api/rfem/aluminum_design/aluminum_member_transverse_weld_pb2.py
dlubal_api-2.13.1.dist-info/METADATA
dlubal_api-2.13.1.dist-info/WHEEL
dlubal_api-2.13.1.dist-info/top_level.txt
dlubal_api-2.13.1.dist-info/RECORD
