Metadata-Version: 2.4
Name: dlubal.api
Version: 2.13.1
Summary: Python Client Library for Dlubal Software APIs powered by gRPC
Author-email: Dlubal Software <api@dlubal.com>
License-Expression: MIT
Classifier: Programming Language :: Python :: 3
Classifier: Programming Language :: Python :: 3.10
Classifier: Programming Language :: Python :: 3.11
Classifier: Programming Language :: Python :: 3.12
Requires-Python: >=3.10
Requires-Dist: grpcio==1.68.0
Requires-Dist: grpcio-tools==1.68.0
Requires-Dist: pandas==2.2.3
